fastmcp_file_server/__init__.py
fastmcp_file_server/cli.py
fastmcp_file_server/server.py
fastmcp_file_server-0.1.0.dist-info/METADATA
fastmcp_file_server-0.1.0.dist-info/WHEEL
fastmcp_file_server-0.1.0.dist-info/entry_points.txt
fastmcp_file_server-0.1.0.dist-info/licenses/LICENSE
fastmcp_file_server-0.1.0.dist-info/RECORD
