Metadata-Version: 2.4
Name: fastmcp-file-server
Version: 0.1.0
Summary: Secure MCP file server with multi-tier authentication
Project-URL: Homepage, https://github.com/Luxshan2000/fastmcp-file-server
Project-URL: Repository, https://github.com/Luxshan2000/fastmcp-file-server
Project-URL: Issues, https://github.com/Luxshan2000/fastmcp-file-server/issues
Author: FastMCP File Server Contributors
License: MIT
License-File: LICENSE
Keywords: ai-assistant,authentication,claude-desktop,fastmcp,file-operations,file-server,mcp,model-context-protocol,secure-server
Classifier: Development Status :: 4 - Beta
Classifier: Intended Audience :: Developers
Classifier: License :: OSI Approved :: MIT License
Classifier: Programming Language :: Python :: 3
Classifier: Programming Language :: Python :: 3.10
Classifier: Programming Language :: Python :: 3.11
Classifier: Programming Language :: Python :: 3.12
Classifier: Topic :: Internet :: WWW/HTTP :: HTTP Servers
Classifier: Topic :: Software Development :: Libraries :: Python Modules
Classifier: Topic :: System :: Filesystems
Requires-Python: >=3.10
Requires-Dist: fastmcp>=0.1.0
Requires-Dist: pandas>=2.0.0
Requires-Dist: pillow>=10.0.0
Requires-Dist: python-dotenv>=1.0.0
Requires-Dist: reportlab>=4.0.0
Requires-Dist: requests>=2.28.0
